moco_explorer/__init__.py
moco_explorer/cli.py
moco_explorer/const.py
moco_explorer/commands/__init__.py
moco_explorer/commands/activity/__init__.py
moco_explorer/commands/activity/commands.py
moco_explorer/commands/company/__init__.py
moco_explorer/commands/company/commands.py
moco_explorer/commands/config/__init__.py
moco_explorer/commands/config/commands.py
moco_explorer/commands/contact/__init__.py
moco_explorer/commands/contact/commands.py
moco_explorer/commands/deal/__init__.py
moco_explorer/commands/deal/commands.py
moco_explorer/commands/deal/category/__init__.py
moco_explorer/commands/deal/category/commands.py
moco_explorer/commands/invoice/__init__.py
moco_explorer/commands/invoice/commands.py
moco_explorer/commands/invoice/payment/__init__.py
moco_explorer/commands/invoice/payment/commands.py
moco_explorer/commands/offer/__init__.py
moco_explorer/commands/offer/commands.py
moco_explorer/commands/planning_entry/__init__.py
moco_explorer/commands/planning_entry/commands.py
moco_explorer/commands/project/__init__.py
moco_explorer/commands/project/commands.py
moco_explorer/commands/project/contract/__init__.py
moco_explorer/commands/project/contract/commands.py
moco_explorer/commands/project/expense/__init__.py
moco_explorer/commands/project/expense/commands.py
moco_explorer/commands/project/payment_schedule/__init__.py
moco_explorer/commands/project/payment_schedule/commands.py
moco_explorer/commands/project/recurring_expense/__init__.py
moco_explorer/commands/project/recurring_expense/commands.py
moco_explorer/commands/project/task/__init__.py
moco_explorer/commands/project/task/commands.py
moco_explorer/commands/schedule/__init__.py
moco_explorer/commands/schedule/commands.py
moco_explorer/commands/unit/__init__.py
moco_explorer/commands/unit/commands.py
moco_explorer/commands/user/__init__.py
moco_explorer/commands/user/commands.py
moco_explorer/commands/user/employment/__init__.py
moco_explorer/commands/user/employment/commands.py
moco_explorer-0.3.0.dist-info/AUTHORS.rst
moco_explorer-0.3.0.dist-info/LICENSE
moco_explorer-0.3.0.dist-info/METADATA
moco_explorer-0.3.0.dist-info/WHEEL
moco_explorer-0.3.0.dist-info/entry_points.txt
moco_explorer-0.3.0.dist-info/top_level.txt
moco_explorer-0.3.0.dist-info/RECORD
