Metadata-Version: 2.1
Name: moco-explorer
Version: 0.3.0
Summary: Command line to for exporting data over the moco api
Home-page: https://github.com/sommalia/moco_explorer
Author: sommalia
Author-email: sommalia@tuta.io
License: GNU General Public License v3
Keywords: moco_explorer
Platform: UNKNOWN
Classifier: Development Status :: 2 - Pre-Alpha
Classifier: Intended Audience :: Developers
Classifier: License :: OSI Approved :: GNU General Public License v3 (GPLv3)
Classifier: Natural Language :: English
Classifier: Programming Language :: Python :: 3
Classifier: Programming Language :: Python :: 3.5
Classifier: Programming Language :: Python :: 3.6
Classifier: Programming Language :: Python :: 3.7
Classifier: Programming Language :: Python :: 3.8
Requires-Python: >=3.5
Requires-Dist: Click (>=7.0)
Requires-Dist: moco-wrapper
